{"inkVersion":20,"root":[["^Jovem, por favor tome cuidado com as raízes elas... Estão me matando","\n","ev","str","^Aqui uma poção para você","/str","/ev",{"*":"0.c-0","flg":20},{"c-0":["\n","^Eu já tentei, mas não é em todas as pessoas que funciona essa poção, infelizmente meu destino é morrer. Por sorte pude lhe encontrar. Aqui fique com minhas botas, infelizmentemente não posso entregar para meu filho como herança pois ele também é falecido devido ás incontáveis missões do rei em enviar soldados, mas espero que possa fazer diferença ao longo de sua jornada. Ela o ajudará a saltar mais alto.","\n",["ev","str","^Uma pena ele ter falecido dessa forma, espero que descanse em paz.","/str","/ev",{"*":".^.c-0","flg":20},{"c-0":["\n","end",{"->":"0.g-0"},{"#f":5}]}],{"#f":5}],"g-0":["done",{"#f":5}]}],"done",{"#f":1}],"listDefs":{}}